demo/__init__.py
demo/generator.py
demo/read_data.py
demo/recorder.py
demo/run.py
demo/run_adr.py
demo/run_api.py
demo/run_api_test.py
demo/run_app_test.py
demo/run_hm.py
demo/run_ios.py
demo/run_luna.py
demo/run_web.py
demo/run_web_test.py
demo/web_recorder.py
demo/api/LoginApi.py
demo/api/__init__.py
demo/page/__init__.py
demo/page/adr_page.py
demo/page/hm_page.py
demo/page/ios_page.py
demo/page/pub_page.py
demo/page/web_page.py
demo/pages/__init__.py
demo/pages/adr_page.py
demo/pages/image_page.py
demo/pages/ios_page.py
demo/pages/ocr_page.py
demo/pages/web_page.py
demo/test/__init__.py
demo/test/test_adr.py
demo/test/test_api.py
demo/test/test_hm.py
demo/test/test_web.py
demo/tests/__init__.py
demo/tests/test_adr.py
demo/tests/test_api.py
demo/tests/test_hm.py
demo/tests/test_image.py
demo/tests/test_ios.py
demo/tests/test_luna.py
demo/tests/test_ocr.py
demo/tests/test_web.py
kytest/__init__.py
kytest/case.py
kytest/case_generator.py
kytest/cli.py
kytest/genetor.py
kytest/page.py
kytest/scaffold.py
kytest/testdata.py
kytest/adr/__init__.py
kytest/adr/case.py
kytest/adr/driver.py
kytest/adr/element.py
kytest/adr/page.py
kytest/adr/util.py
kytest/adr/utils.py
kytest/android/__init__.py
kytest/android/case.py
kytest/android/driver.py
kytest/android/element.py
kytest/api/__init__.py
kytest/api/case.py
kytest/api/genetor.py
kytest/api/request.py
kytest/api/service.py
kytest/core/__init__.py
kytest/core/adr/__init__.py
kytest/core/adr/case.py
kytest/core/adr/driver.py
kytest/core/adr/element.py
kytest/core/adr/page.py
kytest/core/adr/remote_adb.py
kytest/core/adr/remote_driver.py
kytest/core/adr/util.py
kytest/core/adr/utils.py
kytest/core/android/__init__.py
kytest/core/android/driver.py
kytest/core/android/element.py
kytest/core/api/__init__.py
kytest/core/api/case.py
kytest/core/api/genetor.py
kytest/core/api/request.py
kytest/core/hm/__init__.py
kytest/core/hm/case.py
kytest/core/hm/driver.py
kytest/core/hm/element.py
kytest/core/hm/page.py
kytest/core/hm/util.py
kytest-0.2.16.dist-info/METADATA
kytest-0.2.16.dist-info/WHEEL
kytest-0.2.16.dist-info/entry_points.txt
kytest-0.2.16.dist-info/top_level.txt
kytest-0.2.16.dist-info/RECORD
