Metadata-Version: 2.1
Name: kytest
Version: 0.2.16
Summary: API/安卓/IOS/WEB/鸿蒙Next平台自动化测试框架
Home-page: https://gitee.com/bluepang2021/ktest_project
Author: 杨康
Author-email: 772840356@qq.com
Platform: API/Android/IOS/HM/WEB
Classifier: Programming Language :: Python :: 3.8
Requires-Python: >=3.8
Requires-Dist: requests (==2.31.0)
Requires-Dist: requests-toolbelt (==1.0.0)
Requires-Dist: urllib3 (==1.26.15)
Requires-Dist: jmespath (==0.9.5)
Requires-Dist: jsonschema (==4.17.0)
Requires-Dist: click (==8.1.7)
Requires-Dist: loguru (==0.7.0)
Requires-Dist: PyYAML (==6.0.1)
Requires-Dist: allure-pytest (==2.9.45)
Requires-Dist: pytest (==6.2.5)
Requires-Dist: pytest-xdist (==2.5.0)
Requires-Dist: pytest-rerunfailures (==10.2)
Requires-Dist: pytest-repeat (==0.9.3)
Provides-Extra: android
Requires-Dist: uiviewer (==1.1.3) ; extra == 'android'
Requires-Dist: uiautomator2 (==3.2.4) ; extra == 'android'
Provides-Extra: hm
Requires-Dist: hmdriver2 (==1.3.0) ; extra == 'hm'
Provides-Extra: ios
Requires-Dist: uiviewer (==1.1.3) ; extra == 'ios'
Requires-Dist: tidevice (==0.12.10) ; extra == 'ios'
Requires-Dist: facebook-wda (==1.5.0) ; extra == 'ios'
Provides-Extra: web
Requires-Dist: playwright (==1.33.0) ; extra == 'web'
